mrjsonstore/__init__.py
mrjsonstore/json_store.py
mrjsonstore-0.5.0.dist-info/LICENSE
mrjsonstore-0.5.0.dist-info/METADATA
mrjsonstore-0.5.0.dist-info/WHEEL
mrjsonstore-0.5.0.dist-info/RECORD
