Metadata-Version: 2.1
Name: mrjsonstore
Version: 0.5.0
Summary: Simple, transparent on-disk JSON store
License: Apache-2.0
Author: Ole Kliemann
Author-email: mail@olekliemann.de
Requires-Python: >=3.12
Classifier: License :: OSI Approved :: Apache Software License
Classifier: Programming Language :: Python :: 3
Classifier: Programming Language :: Python :: 3.12
Requires-Dist: atomicwrites (>=1.4.1,<2.0.0)
Requires-Dist: drresult (>=0.6.0,<0.7.0)
Requires-Dist: pyyaml (>=6.0.2,<7.0.0)
Requires-Dist: types-pyyaml (>=6.0.12.20240917,<7.0.0.0)
